{
  "meta": {
    "created_at": "2025-01-01",
    "description": "Lịch sử giá Bitcoin và Vàng, cập nhật mỗi ngày"
  },
  "records": [
    {
      "date": "2026-03-17",
      "btc_usd": 73833,
      "btc_change_24h": -0.6,
      "btc_market_cap": 1475696331128.4807,
      "btc_volume_24h": 56435531343.37965,
      "gold_usd_oz": 5017.85,
      "gold_usd_gram": 161.33,
      "gold_vnd_gram": 4226775,
      "fetched_at": "2026-03-17T13:49:01Z"
    },
    {
      "date": "2026-03-18",
      "btc_usd": 74538,
      "btc_change_24h": -0.43,
      "btc_market_cap": 1491174886677.6973,
      "btc_volume_24h": 42788296052.01766,
      "gold_usd_oz": 4989.73,
      "gold_usd_gram": 160.42,
      "gold_vnd_gram": 4201802,
      "fetched_at": "2026-03-18T03:35:35Z"
    },
    {
      "date": "2026-03-19",
      "btc_usd": 71387,
      "btc_change_24h": -4.25,
      "btc_market_cap": 1430486468675.5256,
      "btc_volume_24h": 47631380584.90103,
      "gold_usd_oz": 4846.28,
      "gold_usd_gram": 155.81,
      "gold_vnd_gram": 4085411,
      "fetched_at": "2026-03-19T03:35:51Z"
    },
    {
      "date": "2026-03-20",
      "btc_usd": 70529,
      "btc_change_24h": -1.41,
      "btc_market_cap": 1410766865536.851,
      "btc_volume_24h": 44801381088.283615,
      "gold_usd_oz": 4735.37,
      "gold_usd_gram": 152.25,
      "gold_vnd_gram": 3988541,
      "fetched_at": "2026-03-20T03:25:42Z"
    },
    {
      "date": "2026-03-21",
      "btc_usd": 70740,
      "btc_change_24h": 0.4,
      "btc_market_cap": 1414570336471.163,
      "btc_volume_24h": 37178240103.80822,
      "gold_usd_oz": 4517.13,
      "gold_usd_gram": 145.23,
      "gold_vnd_gram": 3794550,
      "fetched_at": "2026-03-21T03:14:28Z"
    },
    {
      "date": "2026-03-22",
      "btc_usd": 69371,
      "btc_change_24h": -1.81,
      "btc_market_cap": 1389067340416.615,
      "btc_volume_24h": 27563008913.897305,
      "gold_usd_oz": 4508.27,
      "gold_usd_gram": 144.94,
      "gold_vnd_gram": 3792588,
      "fetched_at": "2026-03-22T03:34:48Z"
    },
    {
      "date": "2026-03-23",
      "btc_usd": 68154,
      "btc_change_24h": -1.82,
      "btc_market_cap": 1363723544118.4604,
      "btc_volume_24h": 28623871484.297558,
      "gold_usd_oz": 4363.69,
      "gold_usd_gram": 140.3,
      "gold_vnd_gram": 3671488,
      "fetched_at": "2026-03-23T03:39:19Z"
    },
    {
      "date": "2026-03-24",
      "btc_usd": 70523,
      "btc_change_24h": 3.43,
      "btc_market_cap": 1410635442230.518,
      "btc_volume_24h": 51652018515.88558,
      "gold_usd_oz": 4370.86,
      "gold_usd_gram": 140.53,
      "gold_vnd_gram": 3692550,
      "fetched_at": "2026-03-24T03:30:07Z"
    },
    {
      "date": "2026-03-25",
      "btc_usd": 70609,
      "btc_change_24h": 0.21,
      "btc_market_cap": 1411941171557.3235,
      "btc_volume_24h": 40787418901.3728,
      "gold_usd_oz": 4569.53,
      "gold_usd_gram": 146.91,
      "gold_vnd_gram": 3849672,
      "fetched_at": "2026-03-25T03:33:14Z"
    },
    {
      "date": "2026-03-26",
      "btc_usd": 70851,
      "btc_change_24h": 0.2,
      "btc_market_cap": 1417088334879.7642,
      "btc_volume_24h": 34918513391.38745,
      "gold_usd_oz": 4515.96,
      "gold_usd_gram": 145.19,
      "gold_vnd_gram": 3808628,
      "fetched_at": "2026-03-26T03:43:42Z"
    }
  ]
}